{"children": [{"children": [{"name": "Data Science Foundations: Data Mining",
  "value": 100},
 {"name": "Data Science Foundations: Fundamentals", "value": 100},
 {"name": "Learning Data Governance", "value": 100}],
"name": "Data Science"},
{"children": [{"name": "Excel 2016: Managing and Analyzing Data",
  "value": 100},
 {"name": "pandas Essential Training", "value": 100},
 {"name": "Data Visualization: Storytelling", "value": 100}],
"name": "Data Analytics"},
{"children": [{"name": "Online Marketing Foundations: Digital Marketing Research",
  "value": 100},
 {"name": "Introduction to PPC with Google AdWords and Bing Ads",
  "value": 100},
 {"name": "Marketing Analytics: Presenting Digital Marketing Data",
  "value": 100},
 {"name": "Advanced SEO: Developing an SEO-Friendly Website", "value": 100},
 {"name": "SEO Foundations", "value": 100},
 {"name": "Writing a Marketing Plan", "value": 100},
 {"name": "Yo Santosa, Branding Expert", "value": 100}],
"name": "Marketing"},
{"children": [{"name": "Processing and Interchanging JSON Data",
  "value": 100}],
"name": "Developement"},
{"children": [{"name": "Stay Lean with Kanban", "value": 100}],
"name": "Project Management"},
{"children": [{"name": "Graphic Design Foundations: Layout and Composition",
  "value": 100},
 {"name": "Learning Graphic Design: Layouts", "value": 100},
 {"name": "Universal Principles of Design", "value": 100}],
"name": "Design"},
{"children": [{"name": "Programming Foundations: Fundamentals",
  "value": 100},
 {"name": "Computer Science Principles: Digital Information",
  "value": 100}],
"name": "Development"}],
"name": "uni"}